{
  "actor_context": {
    "actor_ref_token": "urn:te:actor-token:consent-service-001",
    "actor_type": "service",
    "organisation_ref_token": "urn:te:org-token:care-provider-b",
    "role_code": "consent-controller"
  },
  "event_facts": {
    "effective_at": "2026-07-01T07:00:00Z",
    "new_state": "active",
    "previous_state": "draft",
    "transition_reason_code": "subject-request"
  },
  "event_type": "consent-state-transition",
  "input_version": "1.0.0",
  "object_contexts": [
    {
      "object_ref_token": "urn:te:consent-token:fixture-001",
      "object_role": "consent",
      "resource_class": "consent-record",
      "resource_version_token": "3",
      "subject_ref_token": "urn:te:subject-token:fixture-001"
    }
  ],
  "occurred_at": "2026-07-01T07:00:00Z",
  "outcome": {
    "code": "success"
  },
  "policy_context": {
    "consent_binding": {
      "consent_ref_token": "urn:te:consent-token:fixture-001",
      "consent_state": "active",
      "consent_version": "3"
    },
    "policy_binding": {
      "policy_ref_token": "urn:te:policy-token:monitoring-access",
      "policy_version": "2026-07"
    }
  },
  "privacy_profile": {
    "minimisation_profile": "TE-PHM-Min-1",
    "retention_class": "research-reference",
    "tokenisation_profile": "TE-Token-Pseudonymous-1"
  },
  "purpose_code": "consent-management",
  "source_boundary": {
    "key_id": "urn:te:key:fixture-emitter-v1",
    "organisation_ref_token": "urn:te:org-token:monitoring-provider-a",
    "source_id": "urn:te:emitter:monitoring-boundary-a",
    "source_role_code": "monitoring-boundary",
    "time_source": {
      "max_skew_ms": 1000,
      "precision_ms": 1,
      "source_id": "urn:te:time-source:fixture-clock"
    }
  },
  "source_event_id": "urn:te:event:consent-grant-001",
  "subject_context": {
    "rotation_scope": "fixture-study",
    "status": "pseudonymous",
    "subject_ref_token": "urn:te:subject-token:fixture-001",
    "token_system": "urn:te:token-system:cmpb-fixture-v1"
  }
}
